{
  "symbol": "MOONMOON",
  "address": "0x0e0e877894a101Ad8711AE3A0194Fa44Ca837a79",
  "decimals": 9,
  "name": "MoonMoon",
  "ens_address": "",
  "website": "https://moonmoon.cash",
  "logo": {
    "src": "",
    "width": "",
    "height": "",
    "ipfs_hash": ""
  },
  "support": {
    "email": "",
    "url": ""
  },
  "social": {
    "blog": "",
    "chat": "",
    "discord": "",
    "facebook": "",
    "forum": "",
    "github": "",
    "gitter": "",
    "instagram": "",
    "linkedin": "",
    "reddit": "",
    "slack": "",
    "telegram": "",
    "twitter": "",
    "youtube": ""
  }
}