{
  "symbol": "DEEZNUTS",
  "address": "0x741F72BC9E29f662F2Eb41c5aB450A2cA33bE57D",
  "decimals": 18,
  "name": "Deez Nuts",
  "ens_address": "",
  "website": "https://www.deeznutscoin.com",
  "logo": {
    "src": "",
    "width": "",
    "height": "",
    "ipfs_hash": ""
  },
  "support": {
    "email": "",
    "url": ""
  },
  "social": {
    "blog": "",
    "chat": "",
    "discord": "",
    "facebook": "",
    "forum": "",
    "github": "",
    "gitter": "",
    "instagram": "",
    "linkedin": "",
    "reddit": "",
    "slack": "",
    "telegram": "",
    "twitter": "",
    "youtube": ""
  }
}