{
  "symbol": "FETA",
  "address": "0xcB5EDCB7A2aDe21Ae4A695A5c7fFB7Aa01DFaA5d",
  "decimals": 9,
  "name": "FetaToken",
  "ens_address": "",
  "website": "https://fetatoken.com/",
  "logo": {
    "src": "",
    "width": "",
    "height": "",
    "ipfs_hash": ""
  },
  "support": {
    "email": "",
    "url": ""
  },
  "social": {
    "blog": "",
    "chat": "",
    "discord": "",
    "facebook": "",
    "forum": "",
    "github": "",
    "gitter": "",
    "instagram": "",
    "linkedin": "",
    "reddit": "",
    "slack": "",
    "telegram": "",
    "twitter": "",
    "youtube": ""
  }
}